{"professor":"Auri","departamento":"IF","atividades":[{"id":1,"peso":9},{"id":2,"peso":17},{"id":3,"peso":13},{"id":4,"peso":8},{"id":5,"peso":7},{"id":6,"peso":15},{"id":7,"peso":19},{"id":8,"peso":3},{"id":9,"peso":8},{"id":10,"peso":9},{"id":11,"peso":0},{"id":12,"peso":12},{"id":13,"peso":19},{"id":14,"peso":14},{"id":15,"peso":14},{"id":16,"peso":1},{"id":17,"peso":7},{"id":18,"peso":3},{"id":19,"peso":2},{"id":20,"peso":20},{"id":21,"peso":5},{"id":22,"peso":6},{"id":23,"peso":17},{"id":24,"peso":13},{"id":25,"peso":13},{"id":26,"peso":2},{"id":27,"peso":9},{"id":28,"peso":19},{"id":29,"peso":17},{"id":30,"peso":10},{"id":31,"peso":6},{"id":32,"peso":9},{"id":33,"peso":19},{"id":34,"peso":2},{"id":35,"peso":5},{"id":36,"peso":14},{"id":37,"peso":7},{"id":38,"peso":5},{"id":39,"peso":2},{"id":40,"peso":20},{"id":41,"peso":19},{"id":42,"peso":2},{"id":43,"peso":16},{"id":44,"peso":14},{"id":45,"peso":13},{"id":46,"peso":12},{"id":47,"peso":1},{"id":48,"peso":3},{"id":49,"peso":9},{"id":50,"peso":17},{"id":51,"peso":19},{"id":52,"peso":20},{"id":53,"peso":1},{"id":54,"peso":6},{"id":55,"peso":3},{"id":56,"peso":14},{"id":57,"peso":13},{"id":58,"peso":8},{"id":59,"peso":8},{"id":60,"peso":0},{"id":61,"peso":14},{"id":62,"peso":1},{"id":63,"peso":8},{"id":64,"peso":17},{"id":65,"peso":2},{"id":66,"peso":16},{"id":67,"peso":1},{"id":68,"peso":2},{"id":69,"peso":19},{"id":70,"peso":14},{"id":71,"peso":0},{"id":72,"peso":5},{"id":73,"peso":2},{"id":74,"peso":19},{"id":75,"peso":14},{"id":76,"peso":12},{"id":77,"peso":0},{"id":78,"peso":8},{"id":79,"peso":14},{"id":80,"peso":2},{"id":81,"peso":4},{"id":82,"peso":9},{"id":83,"peso":12},{"id":84,"peso":14},{"id":85,"peso":20},{"id":86,"peso":19},{"id":87,"peso":4},{"id":88,"peso":15},{"id":89,"peso":9},{"id":90,"peso":16},{"id":91,"peso":5},{"id":92,"peso":0},{"id":93,"peso":3},{"id":94,"peso":14},{"id":95,"peso":11},{"id":96,"peso":1},{"id":97,"peso":15},{"id":98,"peso":9},{"id":99,"peso":2},{"id":100,"peso":10}]}